immunipy-0.1.0.dist-info/METADATA
immunipy-0.1.0.dist-info/WHEEL
immunipy-0.1.0.dist-info/entry_points.txt
immunipy-0.1.0.dist-info/license_files/LICENSE
immunipy/main.py
immunipy/__init__.py
immunipy/immunipy.cpython-39-x86_64-linux-gnu.so
immunipy-0.1.0.dist-info/RECORD
