Metadata-Version: 2.3
Name: immunipy
Version: 0.1.0
Classifier: Programming Language :: Rust
Classifier: Programming Language :: Python :: Implementation :: CPython
Classifier: Programming Language :: Python :: Implementation :: PyPy
Requires-Dist: typer
License-File: LICENSE
Summary: A Python SCA tool that acts as a watchdog, keeping an eye out for security vulnerabilities and reporting them promptly.
Home-Page: https://github.com/rohaquinlop/immunipy
Author: Robin Quintero <rohaquinlop301@gmail.com>
Author-email: Robin Quintero <rohaquinlop301@gmail.com>
License: MIT
Requires-Python: >=3.7
Project-URL: Source Code, https://github.com/rohaquinlop/immunipy
